gradle.properties
hexdoc_yaha/__gradle_version__.py
hexdoc_yaha/__init__.py
hexdoc_yaha/__version__.py
hexdoc_yaha/_hooks.py
hexdoc_yaha/py.typed
hexdoc_yaha/_export/.gitignore
hexdoc_yaha/_export/__init__.py
hexdoc_yaha/_export/generated/__init__.py
hexdoc_yaha/_export/generated/yaha.hexdoc.json
hexdoc_yaha/_export/generated/yaha.patterns.hexdoc.json
hexdoc_yaha/_export/generated/assets/hexcasting/patchouli_books/thehexbook/en_us/entries/items/bundles.json
hexdoc_yaha/_export/generated/assets/hexcasting/patchouli_books/thehexbook/en_us/entries/patterns/spells/armaments.json
hexdoc_yaha/_export/generated/assets/hexcasting/patchouli_books/thehexbook/en_us/entries/patterns/spells/yahaspells.json
hexdoc_yaha/_export/generated/assets/yaha/lang/en_us.flatten.json5
hexdoc_yaha/_export/generated/assets/yaha/lang/en_us.json
hexdoc_yaha/_export/generated/assets/yaha/lang/zh_cn.flatten.json5
hexdoc_yaha/_export/generated/assets/yaha/lang/zh_cn.json
hexdoc_yaha/_export/generated/assets/yaha/models/item/pouch.json
hexdoc_yaha/_export/generated/assets/yaha/models/item/pouch_filled.json
hexdoc_yaha/_export/generated/assets/yaha/models/item/spindle.json
hexdoc_yaha/_export/generated/assets/yaha/models/item/spindle_filled.json
hexdoc_yaha/_export/generated/assets/yaha/models/item/time_bomb.json
hexdoc_yaha/_export/generated/assets/yaha/textures/entity/anvil.png
hexdoc_yaha/_export/generated/assets/yaha/textures/entity/paper_plane.png
hexdoc_yaha/_export/generated/assets/yaha/textures/gui/container/bundles.png
hexdoc_yaha/_export/generated/assets/yaha/textures/item/pouch.png
hexdoc_yaha/_export/generated/assets/yaha/textures/item/pouch_filled.png
hexdoc_yaha/_export/generated/assets/yaha/textures/item/spindle.png
hexdoc_yaha/_export/generated/assets/yaha/textures/item/spindle_filled.png
hexdoc_yaha/_export/generated/assets/yaha/textures/item/time_bomb.png
hexdoc_yaha/_export/generated/data/yaha/recipes/pouch.json
hexdoc_yaha/_export/generated/data/yaha/recipes/spindle.json
hexdoc_yaha-0.2.1.1.0.dist-info/METADATA
hexdoc_yaha-0.2.1.1.0.dist-info/WHEEL
hexdoc_yaha-0.2.1.1.0.dist-info/entry_points.txt
hexdoc_yaha-0.2.1.1.0.dist-info/licenses/LICENSE.txt
hexdoc_yaha-0.2.1.1.0.dist-info/RECORD
