Metadata-Version: 2.4
Name: hexdoc-yaha
Version: 0.2.1.1.0
Summary: A Hexcasting addon that adds an assorted handful of spells, patterns and items!
Project-URL: Homepage, https://therobbie73.github.io/yaha
Project-URL: Source, https://github.com/TheRobbie73/yaha
Author: TheRobbie73
License-File: LICENSE.txt
Keywords: hexdoc
Requires-Python: >=3.12
Requires-Dist: hexdoc-hexcasting~=0.11.2.1.0
